pyredpocket/__init__.py
pyredpocket/client.py
pyredpocket/details.py
pyredpocket-0.1.5.dist-info/LICENSE
pyredpocket-0.1.5.dist-info/METADATA
pyredpocket-0.1.5.dist-info/WHEEL
pyredpocket-0.1.5.dist-info/top_level.txt
pyredpocket-0.1.5.dist-info/RECORD
