Metadata-Version: 2.1
Name: pyredpocket
Version: 0.1.5
Summary: Python Interface for RedPocket Mobile Data
Home-page: https://github.com/ronnie-llamado/pyRedPocket
Author: Ronnie Llamado
Author-email: llamado.ronnie@gmail.com
License: MIT
Platform: UNKNOWN
Classifier: Programming Language :: Python :: 3.6
Classifier: Programming Language :: Python :: 3.7
Classifier: Programming Language :: Python :: 3.8
Classifier: Programming Language :: Python :: 3.9
Requires-Python: >=3.6
Requires-Dist: requests
